customtkinterthemes/__init__.py
customtkinterthemes/theme_manager.py
customtkinterthemes/Fonts/__init__.py
customtkinterthemes/Fonts/haxrcorp-4089.ttf
customtkinterthemes/Themes/__init__.py
customtkinterthemes/Themes/autumn.json
customtkinterthemes/Themes/blue.json
customtkinterthemes/Themes/breeze.json
customtkinterthemes/Themes/carrot.json
customtkinterthemes/Themes/cherry.json
customtkinterthemes/Themes/coffee.json
customtkinterthemes/Themes/dark-blue.json
customtkinterthemes/Themes/extreme.json
customtkinterthemes/Themes/flipperzero.json
customtkinterthemes/Themes/green.json
customtkinterthemes/Themes/hacked.json
customtkinterthemes/Themes/lavender.json
customtkinterthemes/Themes/marsh.json
customtkinterthemes/Themes/metal.json
customtkinterthemes/Themes/midnight.json
customtkinterthemes/Themes/orange.json
customtkinterthemes/Themes/orangish.json
customtkinterthemes/Themes/patina.json
customtkinterthemes/Themes/pink.json
customtkinterthemes/Themes/red.json
customtkinterthemes/Themes/rime.json
customtkinterthemes/Themes/rose.json
customtkinterthemes/Themes/sky.json
customtkinterthemes/Themes/violet.json
customtkinterthemes/Themes/yellow.json
customtkinterthemes-1.0.2.dist-info/licenses/LICENSE
customtkinterthemes-1.0.2.dist-info/METADATA
customtkinterthemes-1.0.2.dist-info/WHEEL
customtkinterthemes-1.0.2.dist-info/top_level.txt
customtkinterthemes-1.0.2.dist-info/RECORD
