Metadata-Version: 2.4
Name: customtkinterthemes
Version: 1.0.2
Summary: A theme manager for CustomTkinter
Home-page: https://github.com/rigvedmaanas/CustomTkinterThemes
Author: Rigved Maanas
Author-email: rigvedmaanas@gmail.com
Classifier: Programming Language :: Python :: 3
Classifier: Operating System :: OS Independent
Requires-Python: >=3.7
License-File: LICENSE
Requires-Dist: customtkinter
Dynamic: author
Dynamic: author-email
Dynamic: classifier
Dynamic: description
Dynamic: description-content-type
Dynamic: home-page
Dynamic: license-file
Dynamic: requires-dist
Dynamic: requires-python
Dynamic: summary
